LICENSE
MANIFEST.in
README.md
setup.py
mathprolib/Fraction.py
mathprolib/Inf_digits_float.py
mathprolib/Scientific.py
mathprolib/__init__.py
mathprolib/float2Fraction.py
mathprolib/help.py
mathprolib/linear_algebra.py
mathprolib/polynomials.py
mathprolib/simple.py
mathprolib.egg-info/PKG-INFO
mathprolib.egg-info/SOURCES.txt
mathprolib.egg-info/dependency_links.txt
mathprolib.egg-info/top_level.txt