Metadata-Version: 2.1
Name: mathprolib
Version: 0.1.7
Summary: 数学运算专用库，使用简单，内含三角学、分数、科学计算法等实用功能。
Home-page: https://gitee.com/index-1048576/mathlib
Author: 2097152, Toby_Lai, Programmer-1048576
Author-email: cookies_wrmdcxy@126.com
License: MIT
Platform: UNKNOWN
Classifier: License :: OSI Approved :: MIT License
Classifier: Programming Language :: Python
Classifier: Programming Language :: Python :: 3
Classifier: Programming Language :: Python :: 3.6
Classifier: Programming Language :: Python :: Implementation :: CPython
Classifier: Programming Language :: Python :: Implementation :: PyPy
Requires-Python: >=3.6.0
